pipex/__init__.py
pipex/config.yml
pipex/dotdict.py
pipex/store.py
pipex/tasks.py
pipex/prefect/__init__.py
pipex/prefect/logging.yml
pipex/prefect/logging_daskdistributed.yaml
pipex/prefect/logging_default.yml
pipex/prefect/skipped.py
pipex/prefect/tasks.py
pipex/prefect/utils.py
pipex-8.0.0.dist-info/METADATA
pipex-8.0.0.dist-info/WHEEL
pipex-8.0.0.dist-info/top_level.txt
pipex-8.0.0.dist-info/RECORD
