Metadata-Version: 2.1
Name: pipex
Version: 8.0.0
Summary: Purpose
Home-page: http://github.com/simonm3/pipex.git
License: UNKNOWN
Platform: UNKNOWN
Requires-Dist: PyYAML
Requires-Dist: prefect
